meiga/VERSION
meiga/__init__.py
meiga/alias.py
meiga/deprecation.py
meiga/error.py
meiga/failures.py
meiga/handlers.py
meiga/misc.py
meiga/no_given_value.py
meiga/on_failure_exception.py
meiga/public_api.py
meiga/py.typed
meiga/result.py
meiga/assertions/__init__.py
meiga/assertions/assert_failure.py
meiga/assertions/assert_success.py
meiga/decorators/__init__.py
meiga/decorators/async_decoration_error.py
meiga/decorators/async_early_return.py
meiga/decorators/early_return.py
meiga/decorators/to_result.py
meiga/decorators/unexpected_decoration_order_error.py
meiga-1.10.1.dist-info/METADATA
meiga-1.10.1.dist-info/WHEEL
meiga-1.10.1.dist-info/licenses/LICENSE
meiga-1.10.1.dist-info/RECORD
